reaper_cleanup/__init__.py
reaper_cleanup/cli.py
reaper_cleanup/config.py
reaper_cleanup/core.py
reaper_cleanup-0.1.0.dist-info/METADATA
reaper_cleanup-0.1.0.dist-info/WHEEL
reaper_cleanup-0.1.0.dist-info/entry_points.txt
reaper_cleanup-0.1.0.dist-info/top_level.txt
reaper_cleanup-0.1.0.dist-info/RECORD
