Metadata-Version: 2.4
Name: reaper-cleanup
Version: 0.1.0
Summary: CLI tool to clean up unused media files from Reaper projects
Author: MateusMolina
License-Expression: MIT
Project-URL: Homepage, https://github.com/MateusMolina/reaper-cleanup
Project-URL: Repository, https://github.com/MateusMolina/reaper-cleanup
Project-URL: Issues, https://github.com/MateusMolina/reaper-cleanup/issues
Keywords: reaper,audio,cleanup,media,daw
Classifier: Development Status :: 4 - Beta
Classifier: Environment :: Console
Classifier: Programming Language :: Python :: 3
Classifier: Topic :: Multimedia :: Sound/Audio
Classifier: Topic :: Utilities
Requires-Python: >=3.8
Requires-Dist: click>=8.0.0
